dotdotdot/__init__.py
dotdotdot/config.py
dotdotdot-1.0.12.dist-info/licenses/LICENSE
dotdotdot-1.0.12.dist-info/METADATA
dotdotdot-1.0.12.dist-info/WHEEL
dotdotdot-1.0.12.dist-info/top_level.txt
dotdotdot-1.0.12.dist-info/RECORD
