Metadata-Version: 2.4
Name: dotdotdot
Version: 1.0.12
Summary: Access application configuration using dot notation
Author-email: Nehar Arora <python@nehar.net>
License-Expression: BSD-2-Clause
Project-URL: Homepage, https://github.com/nehararora/dotdotdot
Project-URL: Issues, https://github.com/nehararora/dotdotdot/issues
Classifier: Programming Language :: Python :: 3
Classifier: Operating System :: OS Independent
Classifier: Development Status :: 5 - Production/Stable
Classifier: Topic :: Software Development :: Libraries
Classifier: Intended Audience :: Developers
Requires-Python: >=3.12
License-File: LICENSE
Requires-Dist: PyYAML>=6.0.2
Provides-Extra: dev
Requires-Dist: pytest>=8.3.4; extra == "dev"
Requires-Dist: pytest-cov>=6.2.1; extra == "dev"
Requires-Dist: pytest-pep8>=1.0.6; extra == "dev"
Requires-Dist: pytest-flake8>=1.3.0; extra == "dev"
Requires-Dist: build>=1.3.0; extra == "dev"
Dynamic: license-file
